licomp/__init__.py
licomp/config.py
licomp/interface.py
licomp/main_base.py
licomp/return_codes.py
licomp/data/reply_schema.json
licomp-0.5.21.dist-info/GPL-3.0-or-later.txt
licomp-0.5.21.dist-info/METADATA
licomp-0.5.21.dist-info/WHEEL
licomp-0.5.21.dist-info/top_level.txt
licomp-0.5.21.dist-info/RECORD
