Metadata-Version: 2.1
Name: licomp
Version: 0.5.21
Summary: An interface to generalise license compatibility resources
Home-page: https://github.com/hesa/licomp
Author: Henrik Sanklef
Author-email: hesa@sandklef.com
Classifier: Development Status :: 4 - Beta
Classifier: Environment :: Console
Classifier: Intended Audience :: Developers
Classifier: Intended Audience :: Legal Industry
Classifier: License :: OSI Approved :: GNU General Public License v3 or later (GPLv3+)
Classifier: Natural Language :: English
Classifier: Operating System :: POSIX :: Linux
Classifier: Programming Language :: Python :: 3 :: Only
Classifier: Programming Language :: Python :: 3.6
Classifier: Programming Language :: Python :: 3.7
Classifier: Programming Language :: Python :: 3.8
Classifier: Programming Language :: Python :: 3.9
Classifier: Programming Language :: Python :: 3.10
Classifier: Programming Language :: Python :: 3
Classifier: Topic :: Software Development :: Quality Assurance
Requires-Python: >=3.6
License-File: LICENSES/GPL-3.0-or-later.txt
Requires-Dist: PyYaml
Provides-Extra: dev
Requires-Dist: bump2version ~=1.0 ; extra == 'dev'
Requires-Dist: flake8 ~=7.1 ; extra == 'dev'
Requires-Dist: jsonschema ; extra == 'dev'
Requires-Dist: pytest ; extra == 'dev'
